{"0": "ADHD_diagnosed", "1": "ADHD_fullform", "2": "Affect_of_depression", "3": "Anxiety_attacking_time", "4": "Conduct_disorder", "5": "Gender_Roles_Mental_Health", "6": "Major_Depression", "7": "Negetive_symptoms_Schizophrenia", "8": "PSTD_symptom", "9": "Persistent_Depressive_Disorder", "10": "Postpartum_Depression", "11": "Psychotic_Depression", "12": "Schizophrenia_affects", "13": "Schizophrenia_and_multiple_personality_disorder", "14": "Seasonal_Affective_Disorder", "15": "Signs_of_schizophrenia", "16": "Symptoms_ADHD", "17": "Symptoms_autism_spectrum", "18": "Types_PTSD", "19": "abuse", "20": "addiction_mental_health", "21": "affecting_age_group_eating_disorder", "22": "alternative_treatment_depression", "23": "anxiety_affecting_life", "24": "anxiety_cause", "25": "asking_bot", "26": "asking_help_for_depression", "27": "biploar_treatment", "28": "bipolar_affecting_daily_life", "29": "bipolar_can_be_treated", "30": "bipolar_disorder_symptoms", "31": "bipolar_impact_relationship", "32": "bipolar_in_children", "33": "bipolar_symptom", "34": "bipolar_treatment", "35": "bipolar_triggers", "36": "bot_challenge", "37": "bot_feelings", "38": "bullying_issue", "39": "calming_yourself", "40": "cause_Disruptive_behavior", "41": "cause_PSTD", "42": "cause_Schizophrenia", "43": "cause_eating_disorder", "44": "cause_neurodevelopmental", "45": "cause_of_bipolar", "46": "cause_of_depression", "47": "childhood_trauma_leading_anxiety", "48": "complex_PTSD", "49": "coping_mechanism", "50": "counseling_recoomendation", "51": "deadly_disease_survivor_mental_health", "52": "death_of_loved_one_causing_anxiety", "53": "defination_PSTD", "54": "define_Disruptive_behavior", "55": "define_Neurodevelopmental", "56": "define_Schizophrenia", "57": "define_anxiety", "58": "define_biploar_disorder", "59": "define_depression", "60": "define_dyslexia", "61": "define_eating_disorder", "62": "deine_ADHD", "63": "demotivated", "64": "depression_affecting_life", "65": "depression_anxiety_difference", "66": "depression_symptom", "67": "diabities_as_cause_of_depression", "68": "duration_of_anxiety", "69": "dyslexia_diagnosed", "70": "effect_PSTD", "71": "emotion_overflow", "72": "emotional_talk", "73": "empathaizing", "74": "excersie_helping_anxiety", "75": "expressing_themselves", "76": "exteme_end_suicide", "77": "first_session", "78": "fix_Depression", "79": "genetic_Schizophrenia", "80": "genetic_bipolar", "81": "genetic_cause_anxiety", "82": "genetics_role_in_depression", "83": "get_counseler", "84": "goodbye", "85": "greet", "86": "handleinsult", "87": "having_eating_disorder", "88": "help", "89": "helping_loved_one_PSTD", "90": "highest_depression_rate", "91": "how_coommon_PTSD", "92": "how_long_depression_last", "93": "insecure_feelings", "94": "issue_low_self_esteem", "95": "life_after_depression", "96": "link_between_trauma_schizophrenia", "97": "long_term_effect_eating_disorder", "98": "long_term_effect_schizophrenia", "99": "long_term_effects_PSTD", "100": "love_life", "101": "love_one_Schizophrenia", "102": "love_one_bipolar", "103": "love_one_eating_disorder", "104": "love_validation", "105": "loved_one_depressed", "106": "low_self_esteem", "107": "make_mental_health_better", "108": "medication", "109": "mental_health_concern", "110": "misconception_PSTD", "111": "misconception__eating_disorder", "112": "misconception_depression", "113": "misconception_on_anxiety", "114": "misconception_on_bipolar", "115": "misconception_schizophrenia", "116": "mood_great", "117": "mood_unhappy", "118": "most_Depressed_country", "119": "natural_treatment_anxiety", "120": "natural_treatment_bipolar", "121": "need_of_therapist", "122": "oppositional_defiant_disorder", "123": "oversleepong_cause_Depression", "124": "panic_attacks", "125": "past_making_things_hard", "126": "positive_symptom_Schizophrenia", "127": "pressure_enduring", "128": "prevent_PTSD", "129": "prevention_Disruptive_behavior", "130": "prevention_neurodevelopmental", "131": "random_voices", "132": "rape", "133": "reaching_out_counseling", "134": "recommendation_depression", "135": "reducing_symptom_depression", "136": "risk_factor_anxiety", "137": "sad", "138": "schizophrenia_in_children", "139": "school_interferance_depression", "140": "self_Care_PTSD", "141": "self_harm", "142": "self_help_eating_disorder", "143": "sentiment_bot", "144": "sexual_abuse", "145": "sexual_orientation", "146": "sharing_anxiety_symptoms", "147": "smalltalk_agent_age", "148": "smalltalk_agent_annoying", "149": "smalltalk_agent_answer_my_question", "150": "smalltalk_agent_bad", "151": "smalltalk_agent_be_clever", "152": "smalltalk_agent_beautiful", "153": "smalltalk_agent_birth_date", "154": "smalltalk_agent_boring", "155": "smalltalk_agent_boss", "156": "smalltalk_agent_busy", "157": "smalltalk_agent_chatbot", "158": "smalltalk_agent_clever", "159": "smalltalk_agent_crazy", "160": "smalltalk_agent_fired", "161": "smalltalk_agent_funny", "162": "smalltalk_agent_good", "163": "smalltalk_agent_happy", "164": "smalltalk_agent_hungry", "165": "smalltalk_agent_marry_user", "166": "smalltalk_agent_my_friend", "167": "smalltalk_agent_occupation", "168": "smalltalk_agent_origin", "169": "smalltalk_agent_ready", "170": "smalltalk_agent_real", "171": "smalltalk_agent_residence", "172": "smalltalk_agent_right", "173": "smalltalk_agent_sure", "174": "smalltalk_agent_talk_to_me", "175": "smalltalk_agent_there", "176": "smalltalk_agent_what_they_doing", "177": "smalltalk_appraisal_bad", "178": "smalltalk_appraisal_good", "179": "smalltalk_appraisal_no_problem", "180": "smalltalk_appraisal_thank_you", "181": "smalltalk_appraisal_welcome", "182": "smalltalk_appraisal_well_done", "183": "smalltalk_confirmation_cancel", "184": "smalltalk_confirmation_no", "185": "smalltalk_confirmation_yes", "186": "smalltalk_dialog_hold_on", "187": "smalltalk_dialog_hug", "188": "smalltalk_dialog_i_do_not_care", "189": "smalltalk_dialog_sorry", "190": "smalltalk_dialog_what_do_you_mean", "191": "smalltalk_dialog_wrong", "192": "smalltalk_emotions_ha_ha", "193": "smalltalk_emotions_wow", "194": "smalltalk_greetings_bye", "195": "smalltalk_greetings_goodevening", "196": "smalltalk_greetings_goodmorning", "197": "smalltalk_greetings_goodnight", "198": "smalltalk_greetings_how_are_you", "199": "smalltalk_greetings_nice_to_meet_you", "200": "smalltalk_greetings_nice_to_see_you", "201": "smalltalk_greetings_nice_to_talk_to_you", "202": "smalltalk_greetings_whatsup", "203": "smalltalk_user_angry", "204": "smalltalk_user_back", "205": "smalltalk_user_bored", "206": "smalltalk_user_busy", "207": "smalltalk_user_can_not_sleep", "208": "smalltalk_user_does_not_want_to_talk", "209": "smalltalk_user_excited", "210": "smalltalk_user_going_to_bed", "211": "smalltalk_user_good", "212": "smalltalk_user_happy", "213": "smalltalk_user_has_birthday", "214": "smalltalk_user_here", "215": "smalltalk_user_joking", "216": "smalltalk_user_likes_agent", "217": "smalltalk_user_lonely", "218": "smalltalk_user_looks_like", "219": "smalltalk_user_loves_agent", "220": "smalltalk_user_misses_agent", "221": "smalltalk_user_needs_advice", "222": "smalltalk_user_sad", "223": "smalltalk_user_sleepy", "224": "smalltalk_user_testing_agent", "225": "smalltalk_user_tired", "226": "smalltalk_user_waits", "227": "smalltalk_user_wants_to_see_agent_again", "228": "smalltalk_user_wants_to_talk", "229": "smalltalk_user_will_be_back", "230": "socail_life_effect_neurodevelopmental", "231": "social_Disruptive_behavior", "232": "social_effect_Schizophrenia", "233": "social_life_affect_eating_disorder", "234": "spiritual_treatment_depression", "235": "substance_abuse_depression", "236": "supporting_anxiety_patients", "237": "symptom_Disruptive_behavior", "238": "symptom_Schizophrenia", "239": "symptoms_PSTD", "240": "symptoms__eating_disorder", "241": "symptoms_anxiety", "242": "symptoms_dyslexia", "243": "targeted_age_group", "244": "telljoke", "245": "thanks", "246": "therapist_for_bipolar", "247": "therapy_eating_disorder", "248": "therapy_helping_anxiety", "249": "therapy_schizophrenia", "250": "trauma", "251": "treatment_ADHD", "252": "treatment_Disruptive_behavior", "253": "treatment_PSTD", "254": "treatment_Schizophrenia", "255": "treatment_anxiety", "256": "treatment_ask_anxeity", "257": "treatment_depression", "258": "treatment_dyslexia", "259": "treatment_eating_disorder", "260": "treatment_neurodevelopmental", "261": "triggers_disruptive", "262": "types_Schizophrenia", "263": "types_eating_disorder", "264": "types_of_anxiety", "265": "types_of_bipolar", "266": "types_of_depression", "267": "user_feeling_worthless", "268": "what_happens_during_depression"}